setup.py
tap_news_utils/__init__.py
tap_news_utils/cloudAMQP_client.py
tap_news_utils/mongodb_client.py
tap_news_utils/news_api_client.py
tap_news_utils/news_classifier_client.py
tap_news_utils/news_recommender_client.py
tap_news_utils.egg-info/PKG-INFO
tap_news_utils.egg-info/SOURCES.txt
tap_news_utils.egg-info/dependency_links.txt
tap_news_utils.egg-info/requires.txt
tap_news_utils.egg-info/top_level.txt