Metadata-Version: 1.1
Name: tap-news-utils
Version: 0.0.9
Summary: A small utility package for tap-news project
Home-page: UNKNOWN
Author: Yitong Wu
Author-email: yw4004@nyu.edu
License: UNKNOWN
Platform: UNKNOWN
Classifier: Programming Language :: Python :: 3
Classifier: License :: OSI Approved :: MIT License
Classifier: Operating System :: OS Independent
